s00zzang_cmd/__init__.py
s00zzang_cmd/cmd.py
s00zzang_cmd-0.2.2.dist-info/METADATA
s00zzang_cmd-0.2.2.dist-info/WHEEL
s00zzang_cmd-0.2.2.dist-info/entry_points.txt
s00zzang_cmd-0.2.2.dist-info/top_level.txt
s00zzang_cmd-0.2.2.dist-info/RECORD
